topsis_hardik_102303494/__init__.py
topsis_hardik_102303494/cli.py
topsis_hardik_102303494/topsis.py
topsis_hardik_102303494-0.1.1.dist-info/METADATA
topsis_hardik_102303494-0.1.1.dist-info/WHEEL
topsis_hardik_102303494-0.1.1.dist-info/entry_points.txt
topsis_hardik_102303494-0.1.1.dist-info/top_level.txt
topsis_hardik_102303494-0.1.1.dist-info/RECORD
