Metadata-Version: 2.4
Name: topsis-hardik-102303494
Version: 0.1.1
Summary: TOPSIS implementation for decision making
Author: Hardik
Requires-Python: >=3.8
Requires-Dist: numpy
Requires-Dist: pandas
Dynamic: author
Dynamic: description
Dynamic: description-content-type
Dynamic: requires-dist
Dynamic: requires-python
Dynamic: summary
